Workbook

Sheet Financial_KPI_Data
A1: Date | B1: Month | C1: Quarter | D1: Year | E1: Region | F1: Department | G1: Product Category | H1: Product Name | I1: Revenue | J1: Cost of Goods Sold | K1: Operating Expenses | L1: Gross Profit | M1: Net Profit | N1: Profit Margin % | O1: Sales Volume | P1: Budgeted Revenue | Q1: Actual Revenue | R1: Budget Variance | S1: Customer Segment | T1: Sales Channel
A2: 45294 | B2: January | C2: Q1 | D2: 2024 | E2: West | F2: Operations | G2: Apparel | H2: Running Shoes | I2: 113365.25 | J2: 54524.08 | K2: 15372.89 | L2: =I2-J2 -> 58841.17 | M2: =L2-K2 -> 43468.28 | N2: =IFERROR(M2/I2,0) -> 0.38343566 | O2: 169 | P2: 110734.84 | Q2: 113365.25 | R2: =Q2-P2 -> 2630.41 | S2: Individual | T2: Online
A3: 45307 | B3: January | C3: Q1 | D3: 2024 | E3: South | F3: Marketing | G3: Electronics | H3: Smart Watch | I3: 607220.65 | J3: 312307.55 | K3: 81347.59 | L3: =I3-J3 -> 294913.1 | M3: =L3-K3 -> 213565.51 | N3: =IFERROR(M3/I3,0) -> 0.35170989 | O3: 1004 | P3: 601152 | Q3: 607220.65 | R3: =Q3-P3 -> 6068.65 | S3: SME | T3: Distributor
A4: 45308 | B4: January | C4: Q1 | D4: 2024 | E4: South | F4: Marketing | G4: Electronics | H4: Smartphone X1 | I4: 446972.07 | J4: 205091.95 | K4: 68241.7 | L4: =I4-J4 -> 241880.12 | M4: =L4-K4 -> 173638.42 | N4: =IFERROR(M4/I4,0) -> 0.38847711 | O4: 1155 | P4: 488397.58 | Q4: 446972.07 | R4: =Q4-P4 -> -41425.51 | S4: Corporate | T4: Retail Store
A5: 45315 | B5: January | C5: Q1 | D5: 2024 | E5: East | F5: Finance | G5: FMCG | H5: Shampoo Bottle | I5: 89616.95 | J5: 57129.2 | K5: 16758.63 | L5: =I5-J5 -> 32487.75 | M5: =L5-K5 -> 15729.12 | N5: =IFERROR(M5/I5,0) -> 0.17551501 | O5: 281 | P5: 104246.34 | Q5: 89616.95 | R5: =Q5-P5 -> -14629.39 | S5: Government | T5: Marketplace
A6: 45329 | B6: February | C6: Q1 | D6: 2024 | E6: South | F6: Retail | G6: FMCG | H6: Skin Care Cream | I6: 122247.05 | J6: 72674.5 | K6: 18238.95 | L6: =I6-J6 -> 49572.55 | M6: =L6-K6 -> 31333.6 | N6: =IFERROR(M6/I6,0) -> 0.25631375 | O6: 1390 | P6: 107141.49 | Q6: 122247.05 | R6: =Q6-P6 -> 15105.56 | S6: Corporate | T6: Direct Sales
A7: 45334 | B7: February | C7: Q1 | D7: 2024 | E7: East | F7: Retail | G7: Apparel | H7: Running Shoes | I7: 93008.81 | J7: 49918.26 | K7: 13343.28 | L7: =I7-J7 -> 43090.55 | M7: =L7-K7 -> 29747.27 | N7: =IFERROR(M7/I7,0) -> 0.31983282 | O7: 1875 | P7: 84660.27 | Q7: 93008.81 | R7: =Q7-P7 -> 8348.54 | S7: Retail | T7: Direct Sales
A8: 45337 | B8: February | C8: Q1 | D8: 2024 | E8: North | F8: Operations | G8: Home Appliances | H8: Microwave Oven | I8: 232550.65 | J8: 148602.23 | K8: 42538.71 | L8: =I8-J8 -> 83948.42 | M8: =L8-K8 -> 41409.71 | N8: =IFERROR(M8/I8,0) -> 0.17806749 | O8: 355 | P8: 229412.95 | Q8: 232550.65 | R8: =Q8-P8 -> 3137.7 | S8: SME | T8: Marketplace
A9: 45338 | B9: February | C9: Q1 | D9: 2024 | E9: North | F9: Retail | G9: Furniture | H9: Wooden Dining Table | I9: 79491.65 | J9: 43382 | K9: 11199.16 | L9: =I9-J9 -> 36109.65 | M9: =L9-K9 -> 24910.49 | N9: =IFERROR(M9/I9,0) -> 0.31337241 | O9: 155 | P9: 85867.9 | Q9: 79491.65 | R9: =Q9-P9 -> -6376.25 | S9: Government | T9: Online
A10: 45343 | B10: February | C10: Q1 | D10: 2024 | E10: Central | F10: Marketing | G10: Electronics | H10: Smart Watch | I10: 216669.55 | J10: 130229.23 | K10: 33174.02 | L10: =I10-J10 -> 86440.32 | M10: =L10-K10 -> 53266.3 | N10: =IFERROR(M10/I10,0) -> 0.24584119 | O10: 1719 | P10: 203296.28 | Q10: 216669.55 | R10: =Q10-P10 -> 13373.27 | S10: Individual | T10: Direct Sales
A11: 45343 | B11: February | C11: Q1 | D11: 2024 | E11: East | F11: Finance | G11: FMCG | H11: Shampoo Bottle | I11: 87605.12 | J11: 45831.1 | K11: 12999.77 | L11: =I11-J11 -> 41774.02 | M11: =L11-K11 -> 28774.25 | N11: =IFERROR(M11/I11,0) -> 0.32845398 | O11: 142 | P11: 90298.31 | Q11: 87605.12 | R11: =Q11-P11 -> -2693.19 | S11: Individual | T11: Marketplace
A12: 45346 | B12: February | C12: Q1 | D12: 2024 | E12: West | F12: Retail | G12: Furniture | H12: Wooden Dining Table | I12: 102662.36 | J12: 60872.71 | K12: 14396.84 | L12: =I12-J12 -> 41789.65 | M12: =L12-K12 -> 27392.81 | N12: =IFERROR(M12/I12,0) -> 0.26682428 | O12: 349 | P12: 115185.32 | Q12: 102662.36 | R12: =Q12-P12 -> -12522.96 | S12: SME | T12: Direct Sales
A13: 45358 | B13: March | C13: Q1 | D13: 2024 | E13: West | F13: Finance | G13: Electronics | H13: Tablet Air | I13: 464722.85 | J13: 301504.58 | K13: 53077.94 | L13: =I13-J13 -> 163218.27 | M13: =L13-K13 -> 110140.33 | N13: =IFERROR(M13/I13,0) -> 0.23700218 | O13: 1615 | P13: 476711.08 | Q13: 464722.85 | R13: =Q13-P13 -> -11988.23 | S13: Individual | T13: Marketplace
... A151: 46021 | B151: December | C151: Q4 | D151: 2025 | E151: East | F151: Finance | G151: FMCG | H151: Instant Noodles | I151: 60594.53 | J151: 35201.94 | K151: 12441.56 | L151: =I151-J151 -> 25392.59 | M151: =L151-K151 -> 12951.03 | N151: =IFERROR(M151/I151,0) -> 0.21373266 | O151: 1179 | P151: 56829.47 | Q151: 60594.53 | R151: =Q151-P151 -> 3765.06 | S151: Retail | T151: Direct Sales

Sheet KPI_Summary
A1: Metric | B1: Value
A2: Total Revenue | B2: =SUM(Financial_KPI_Data!I2:I151) -> 31022574
A3: Total Cost of Goods Sold | B3: =SUM(Financial_KPI_Data!J2:J151) -> 17035398
A4: Total Operating Expenses | B4: =SUM(Financial_KPI_Data!K2:K151) -> 4873175.2
A5: Total Gross Profit | B5: =SUM(Financial_KPI_Data!L2:L151) -> 13987176
A6: Total Net Profit | B6: =SUM(Financial_KPI_Data!M2:M151) -> 9114000.6
A7: Overall Profit Margin % | B7: =SUM(Financial_KPI_Data!M2:M151)/SUM(Financial_KPI_Data!I2:I151) -> 0.29378609
A8: Total Budgeted Revenue | B8: =SUM(Financial_KPI_Data!P2:P151) -> 31216118
A9: Total Actual Revenue | B9: =SUM(Financial_KPI_Data!Q2:Q151) -> 31022574
A10: Total Budget Variance | B10: =SUM(Financial_KPI_Data!R2:R151) -> -193544.29
A11: Average Sales Volume | B11: =AVERAGE(Financial_KPI_Data!O2:O151) -> 900.51333
